remove_meta/__init__.py
remove_meta-0.0.5.dist-info/LICENSE
remove_meta-0.0.5.dist-info/METADATA
remove_meta-0.0.5.dist-info/WHEEL
remove_meta-0.0.5.dist-info/entry_points.txt
remove_meta-0.0.5.dist-info/top_level.txt
remove_meta-0.0.5.dist-info/RECORD
